RV32IM_pipeline_FPGA/cpu/supported_modules/mux2to1_32bit.v
module mux2to1_32bit(INPUT1, INPUT2, RESULT, SELECT);
    input [31:0] INPUT1, INPUT2; //declare inputs of the module
    input SELECT;               //declare inputs
    output reg [31:0] RESULT;    //declare outputs

    always @(*)
    begin
      if (SELECT == 1'b1)  //selecting according to the select signal
            RESULT = INPUT2;
      else 
            RESULT = INPUT1;
    end

endmodule

RV32IM_pipeline_FPGA/cpu/interupt_control_unit/interupt_control.v
`include "../supported_modules/mux2to1_32bit.v"

module interupt_control (
        input clk,
        input reset,
        input [31:0] pc_next,
        input interupt_signanl,
        input return_from_isr,
        output [31:0] pc_next_final,
        output [31:0] pc_next_regfile,
        output en_regfile
    );

    reg mux_sel;
    localparam ISR_PC = 500;
    reg en_regfile;
    assign pc_next_regfile = pc_next;

    // state machine states
    localparam NORMAL_STATE = 0,
               ISR_INIT_STATE = 1,
               ISR_STATE = 2;

    reg [1:0] current_state, next_state;

    // mux to select the next pc
    mux2to1_32bit pcMux (pc_next, ISR_PC, pc_next_final, mux_sel);

    // combinational logic to caclculate next stage
    always @* begin
      case (current_state)
        NORMAL_STATE: begin
            if (interupt_signanl == 1'b1)
                next_state = ISR_INIT_STATE;
            else
                next_state = NORMAL_STATE;
        end
        ISR_INIT_STATE:
            next_state = ISR_STATE;
        ISR_STATE: begin
            if (return_from_isr == 1'b1)
                next_state = NORMAL_STATE;
            else
                next_state = ISR_STATE;
        end
      endcase
    end

    // changing the control signaks according to the current state
    always @* begin
      case (current_state)
        NORMAL_STATE: begin
          mux_sel = 1'b0;
        end
        ISR_INIT_STATE: begin
          mux_sel = 1'b1;
        end
        ISR_STATE: begin
            mux_sel = 1'b0;
        end
      endcase
    end

    // state change in to the negative edge of the clock signal
    always @(negedge clk) begin
        if (reset == 1'b1) 
            current_state = NORMAL_STATE;
        else begin
            current_state = next_state;
            if (current_state == ISR_INIT_STATE) 
                en_regfile = 1'b1;
            else
                en_regfile = 1'b0;
        end
    end

    // Save the PC to the register file
    // always @(negedge clk ) begin
    //     if (current_state == ISR_INIT_STATE) 
    //         en_regfile = 1'b1;
    //     else
    //         en_regfile = 1'b0;
    // end


endmodule

RV32IM_pipeline_FPGA/cpu/testbench/testbenchINTERUPT.v
`include "../interupt_control_unit/interupt_control.v"

module testbenchINTERUPT;

    reg [31:0] pc_next;
    wire [31:0] pc_next_final, pc_next_regfile;
    wire en_regfile;
    reg clk, reset, interupt_signanl, return_from_isr;

    interupt_control ic (clk, reset, pc_next, interupt_signanl, return_from_isr, pc_next_final, pc_next_regfile, en_regfile);

    initial begin
        $dumpfile("icu_wavedata.vcd");
        $dumpvars(0, testbenchINTERUPT);
    end

    initial begin
        clk = 1'b0;

        pc_next = 32'd44;
        interupt_signanl = 1'b0;
        return_from_isr = 1'b0;
        reset = 1'b1;

        #10
        reset = 1'b0;
        

        #30
        interupt_signanl = 1'b1;

        #10
        interupt_signanl = 1'b0;

        #50
        return_from_isr = 1'b1;

        #10
        return_from_isr = 1'b0;

        #200
        $finish;
      
    end

    // clock signal generation
    always
    begin
        #10 clk = ~clk;
    end  

endmodule

RV32IM_pipeline_FPGA/cpu/testbench/icu_wavedata.vcd
$date
	Fri Jan  6 14:53:01 2023
$end
$version
	Icarus Verilog
$end
$timescale
	1s
$end
$scope module testbenchINTERUPT $end
$var wire 32 ! pc_next_regfile [31:0] $end
$var wire 32 " pc_next_final [31:0] $end
$var wire 1 # en_regfile $end
$var reg 1 $ clk $end
$var reg 1 % interupt_signanl $end
$var reg 32 & pc_next [31:0] $end
$var reg 1 ' reset $end
$var reg 1 ( return_from_isr $end
$scope module ic $end
$var wire 1 $ clk $end
$var wire 1 % interupt_signanl $end
$var wire 32 ) pc_next [31:0] $end
$var wire 32 * pc_next_regfile [31:0] $end
$var wire 1 ' reset $end
$var wire 1 ( return_from_isr $end
$var wire 32 + pc_next_final [31:0] $end
$var reg 2 , current_state [1:0] $end
$var reg 1 # en_regfile $end
$var reg 1 - mux_sel $end
$var reg 2 . next_state [1:0] $end
$scope module pcMux $end
$var wire 32 / INPUT1 [31:0] $end
$var wire 32 0 INPUT2 [31:0] $end
$var wire 1 - SELECT $end
$var reg 32 1 RESULT [31:0] $end
$upscope $end
$upscope $end
$upscope $end
$enddefinitions $end
#0
$dumpvars
b101100 1
b111110100 0
b101100 /
b0 .
0-
b0 ,
b101100 +
b101100 *
b101100 )
0(
1'
b101100 &
0%
0$
x#
b101100 "
b101100 !
$end
#10
1$
0'
#20
0#
0$
#30
1$
#40
b111110100 "
b111110100 +
b111110100 1
1-
1#
b1 ,
b10 .
0$
1%
#50
1$
0%
#60
b101100 "
b101100 +
b101100 1
0-
0#
b10 ,
0$
#70
1$
#80
0$
#90
1$
#100
b0 ,
b0 .
0$
1(
#110
1$
0(
